bodyig_cpm.py
bodyig_cpm-0.0.3.dist-info/licenses/LICENSE
bodyig_cpm-0.0.3.dist-info/METADATA
bodyig_cpm-0.0.3.dist-info/WHEEL
bodyig_cpm-0.0.3.dist-info/top_level.txt
bodyig_cpm-0.0.3.dist-info/RECORD
