Metadata-Version: 2.4
Name: bodyig-cpm
Version: 0.0.3
Summary: A character-pair merging module for Classical Tibetan.
Author-email: Elya Brown <elyavyale@gmail.com>
Project-URL: Homepage, https://github.com/merzsielen/Bodyig-CPM
Keywords: Classical Tibetan,character-pairs
Classifier: License :: OSI Approved :: MIT License
Classifier: Programming Language :: Python
Classifier: Programming Language :: Python :: 3
Requires-Python: >=3.7
License-File: LICENSE
Provides-Extra: dev
Requires-Dist: bumpver; extra == "dev"
Requires-Dist: pip-tools; extra == "dev"
Dynamic: license-file
